alibabacloud_sddp20190103/__init__.py
alibabacloud_sddp20190103/client.py
alibabacloud_sddp20190103/models/__init__.py
alibabacloud_sddp20190103/models/_create_config_request.py
alibabacloud_sddp20190103/models/_create_config_response.py
alibabacloud_sddp20190103/models/_create_config_response_body.py
alibabacloud_sddp20190103/models/_create_data_limit_request.py
alibabacloud_sddp20190103/models/_create_data_limit_response.py
alibabacloud_sddp20190103/models/_create_data_limit_response_body.py
alibabacloud_sddp20190103/models/_create_rule_request.py
alibabacloud_sddp20190103/models/_create_rule_response.py
alibabacloud_sddp20190103/models/_create_rule_response_body.py
alibabacloud_sddp20190103/models/_create_scan_task_request.py
alibabacloud_sddp20190103/models/_create_scan_task_response.py
alibabacloud_sddp20190103/models/_create_scan_task_response_body.py
alibabacloud_sddp20190103/models/_create_slr_role_request.py
alibabacloud_sddp20190103/models/_create_slr_role_response.py
alibabacloud_sddp20190103/models/_create_slr_role_response_body.py
alibabacloud_sddp20190103/models/_delete_data_limit_request.py
alibabacloud_sddp20190103/models/_delete_data_limit_response.py
alibabacloud_sddp20190103/models/_delete_data_limit_response_body.py
alibabacloud_sddp20190103/models/_delete_rule_request.py
alibabacloud_sddp20190103/models/_delete_rule_response.py
alibabacloud_sddp20190103/models/_delete_rule_response_body.py
alibabacloud_sddp20190103/models/_describe_audit_logs_request.py
alibabacloud_sddp20190103/models/_describe_audit_logs_response.py
alibabacloud_sddp20190103/models/_describe_audit_logs_response_body.py
alibabacloud_sddp20190103/models/_describe_category_template_list_request.py
alibabacloud_sddp20190103/models/_describe_category_template_list_response.py
alibabacloud_sddp20190103/models/_describe_category_template_list_response_body.py
alibabacloud_sddp20190103/models/_describe_category_template_rule_list_request.py
alibabacloud_sddp20190103-1.6.3.dist-info/LICENSE
alibabacloud_sddp20190103-1.6.3.dist-info/METADATA
alibabacloud_sddp20190103-1.6.3.dist-info/WHEEL
alibabacloud_sddp20190103-1.6.3.dist-info/top_level.txt
alibabacloud_sddp20190103-1.6.3.dist-info/RECORD
